{
  "lastUpdatedYear": 2021,
  "lastUpdatedQuarter": "January to March 2023",
  "renewalYearGIS": 2022,
  "oas": {
    "amount": 687.56,
    "amount75": 756.32,
    "incomeLimit": 129757,
    "incomeLimit75": 129757,
    "clawbackIncomeLimit": 79845
  },
  "gis": {
    "singleAmount": 1026.96,
    "singleIncomeLimit": 20832,
    "spouseOasAmount": 618.15,
    "spouseOasIncomeLimit": 27552,
    "spouseNoOasAmount": 1026.96,
    "spouseNoOasIncomeLimit": 49920,
    "spouseAlwAmount": 618.15,
    "spouseAlwIncomeLimit": 38592
  },
  "alw": {
    "alwAmount": 1305.71,
    "alwIncomeLimit": 38592,
    "afsAmount": 1556.51,
    "afsIncomeLimit": 28080
  },
  "topUp": {
    "single": 159.07,
    "married": 45.06
  }
}
